znipy/__init__.py
znipy/core/__init__.py
znipy/core/finder.py
znipy/core/loader.py
znipy/utils/__init__.py
znipy/utils/notebook_to_file.py
znipy-0.1.1.dist-info/LICENSE
znipy-0.1.1.dist-info/METADATA
znipy-0.1.1.dist-info/WHEEL
znipy-0.1.1.dist-info/top_level.txt
znipy-0.1.1.dist-info/RECORD
