Metadata-Version: 2.1
Name: znipy
Version: 0.1.1
Summary: Easy imports from Jupyter Notebooks
Home-page: https://github.com/zincware/ZnIPy
Download-URL: https://github.com/zincware/ZnIPy/archive/beta.tar.gz
Author: zincwarecode
Author-email: zincwarecode@gmail.com
License: UNKNOWN
Keywords: IPython,Jupyter,ZnTrack
Platform: UNKNOWN
Classifier: Development Status :: 3 - Alpha
Classifier: Programming Language :: Python :: 3
Classifier: License :: OSI Approved :: Eclipse Public License 2.0 (EPL-2.0)
Classifier: Operating System :: OS Independent
Requires-Python: >=3.8
License-File: LICENSE
Requires-Dist: IPython
Requires-Dist: nbformat
